app_guard/AppGuard.cpython-38-darwin.so
app_guard/__init__.py
appguard-1.0.2.dist-info/LICENSE
appguard-1.0.2.dist-info/METADATA
appguard-1.0.2.dist-info/WHEEL
appguard-1.0.2.dist-info/top_level.txt
appguard-1.0.2.dist-info/RECORD
